{"trial_id": "00", "hyperparameters": {"space": [{"class_name": "Choice", "config": {"name": "model_type", "default": "random_forest", "conditions": [], "values": ["random_forest", "decision_tree"], "ordered": false}}, {"class_name": "Int", "config": {"name": "n_estimators", "default": null, "conditions": [], "min_value": 10, "max_value": 20, "step": 3, "sampling": null}}, {"class_name": "Int", "config": {"name": "max_depth", "default": null, "conditions": [], "min_value": 3, "max_value": 5, "step": 1, "sampling": null}}], "values": {"model_type": "random_forest", "n_estimators": 19, "max_depth": 3}}, "metrics": {"metrics": {}}, "score": null, "best_step": null, "status": "RUNNING"}